uapi/__init__.py
uapi/_openapi.py
uapi/aiohttp.py
uapi/attrschema.py
uapi/base.py
uapi/cookies.py
uapi/django.py
uapi/flask.py
uapi/openapi.py
uapi/path.py
uapi/py.typed
uapi/quart.py
uapi/requests.py
uapi/responses.py
uapi/shorthands.py
uapi/starlette.py
uapi/status.py
uapi/types.py
uapi/login/__init__.py
uapi/openapi_ui/__init__.py
uapi/openapi_ui/elements.html
uapi/openapi_ui/redoc.html
uapi/openapi_ui/swaggerui.html
uapi/sessions/__init__.py
uapi/sessions/redis.py
uapi-23.3.0.dist-info/METADATA
uapi-23.3.0.dist-info/WHEEL
uapi-23.3.0.dist-info/licenses/LICENSE
uapi-23.3.0.dist-info/RECORD
