Metadata-Version: 2.1
Name: uapi
Version: 23.3.0
Summary: A Python HTTP superframework
Author-email: Tin Tvrtkovic <tinchester@gmail.com>
License: Apache License
License-File: LICENSE
Classifier: Intended Audience :: Developers
Classifier: License :: OSI Approved :: Apache Software License
Classifier: Programming Language :: Python :: 3.10
Classifier: Programming Language :: Python :: 3.11
Classifier: Programming Language :: Python :: 3.12
Classifier: Programming Language :: Python :: Implementation :: CPython
Classifier: Typing :: Typed
Requires-Python: >=3.10
Requires-Dist: attrs>=23.1.0
Requires-Dist: cattrs>=23.2.2
Requires-Dist: incant>=23.2.0
Requires-Dist: itsdangerous
Requires-Dist: orjson>=3.9.10
